contentful_webhook_receiver/__init__.py
contentful_webhook_receiver/admin.py
contentful_webhook_receiver/apps.py
contentful_webhook_receiver/migrations/0001_initial.py
contentful_webhook_receiver/migrations/__init__.py
contentful_webhook_receiver/models.py
contentful_webhook_receiver/serializers.py
contentful_webhook_receiver/signals.py
contentful_webhook_receiver/topics.py
contentful_webhook_receiver/urls.py
contentful_webhook_receiver/views.py
contentful_webhook_receiver-0.8.2.dist-info/METADATA
contentful_webhook_receiver-0.8.2.dist-info/WHEEL
contentful_webhook_receiver-0.8.2.dist-info/licenses/AUTHORS.rst
contentful_webhook_receiver-0.8.2.dist-info/licenses/LICENSE
contentful_webhook_receiver-0.8.2.dist-info/RECORD
