Metadata-Version: 2.4
Name: contentful-webhook-receiver
Version: 0.8.2
Summary: A Django package to receive Webhooks from Contentful as signals
License: MIT
License-File: AUTHORS.rst
License-File: LICENSE
Author: MarcoGlauser
Author-email: github@mglauser.ch
Requires-Python: >=3.9,<3.15
Classifier: License :: OSI Approved :: MIT License
Classifier: Programming Language :: Python :: 3
Classifier: Programming Language :: Python :: 3.9
Classifier: Programming Language :: Python :: 3.10
Classifier: Programming Language :: Python :: 3.11
Classifier: Programming Language :: Python :: 3.12
Classifier: Programming Language :: Python :: 3.13
Classifier: Programming Language :: Python :: 3.14
Requires-Dist: Django (>=4.2,<5.3)
Requires-Dist: djangorestframework (>=3.0.0,<4.0.0)
Project-URL: Repository, https://github.com/MarcoGlauser/contentful-webhook-receiver
